BnSentiment/__init__.py
BnSentiment/classifier
BnSentiment/vectorizer
BnSentiment-0.4.dist-info/LICENSE
BnSentiment-0.4.dist-info/METADATA
BnSentiment-0.4.dist-info/WHEEL
BnSentiment-0.4.dist-info/top_level.txt
BnSentiment-0.4.dist-info/RECORD
