Metadata-Version: 2.1
Name: BnSentiment
Version: 0.4
Summary: UNKNOWN
Home-page: UNKNOWN
Author: Kowsher Ahmed, Avishek Das
Author-email: ahmedshuvo969@gmail.com, avishek.das.ayan@gmail.com
License: MIT
Platform: UNKNOWN
Classifier: Programming Language :: Python :: 3
Classifier: License :: OSI Approved :: MIT License
Classifier: Operating System :: OS Independent
